grounding/__init__.py
grounding/config.py
grounding/chunkers/__init__.py
grounding/chunkers/markdown.py
grounding/chunkers/python_code.py
grounding/clients/fastembed_client.py
grounding/clients/qdrant_client.py
grounding/clients/voyage_client.py
grounding/contracts/chunk.py
grounding/contracts/document.py
grounding/contracts/ids.py
grounding/query/query.py
grounding/scripts/00_convert_notebooks.py
grounding/scripts/00_smoke_test_connections.py
grounding/scripts/01_print_effective_config.py
grounding/scripts/02_ensure_collection_schema.py
grounding/scripts/03_ingest_corpus.py
grounding/scripts/04_query_demo.py
grounding/util/fs_walk.py
grounding/util/hashing.py
grounding/util/mime.py
grounding/util/time.py
rag_mcp_server/__init__.py
rag_mcp_server/__main__.py
rag_mcp_server/config.py
rag_mcp_server/server.py
rag_mcp_server/jobs/__init__.py
rag_mcp_server/jobs/manager.py
rag_mcp_server/jobs/worker.py
rag_mcp_server/tools/__init__.py
rag_mcp_server/tools/diagnostics.py
rag_mcp_server/tools/discovery.py
rag_mcp_server/tools/ingestion.py
rag_mcp_server/tools/retrieval.py
rag_qdrant_voyage-0.1.0.dist-info/METADATA
rag_qdrant_voyage-0.1.0.dist-info/WHEEL
rag_qdrant_voyage-0.1.0.dist-info/entry_points.txt
rag_qdrant_voyage-0.1.0.dist-info/RECORD
