Metadata-Version: 2.4
Name: rag-qdrant-voyage
Version: 0.1.0
Summary: Agentic RAG SDK - MCP server for grounding AI coding agents with Voyage AI + Qdrant hybrid retrieval
Project-URL: Homepage, https://github.com/MattMagg/agentic-rag-sdk
Project-URL: Repository, https://github.com/MattMagg/agentic-rag-sdk
Project-URL: Documentation, https://github.com/MattMagg/agentic-rag-sdk#readme
Project-URL: Issues, https://github.com/MattMagg/agentic-rag-sdk/issues
Author: MattMagg
License-Expression: MIT
Keywords: ai-agents,claude-code,coding-agent,embeddings,grounding,hybrid-search,llm,mcp,model-context-protocol,qdrant,rag,reranking,retrieval-augmented-generation,semantic-search,vector-database,voyage-ai
Classifier: Development Status :: 4 - Beta
Classifier: Intended Audience :: Developers
Classifier: License :: OSI Approved :: MIT License
Classifier: Programming Language :: Python :: 3
Classifier: Programming Language :: Python :: 3.11
Classifier: Programming Language :: Python :: 3.12
Classifier: Topic :: Scientific/Engineering :: Artificial Intelligence
Classifier: Topic :: Software Development :: Libraries :: Python Modules
Classifier: Topic :: Text Processing :: Indexing
Requires-Python: >=3.11
Requires-Dist: fastembed>=0.5.0
Requires-Dist: fastmcp>=2.0.0
Requires-Dist: pydantic-settings>=2.0.0
Requires-Dist: pydantic>=2.0.0
Requires-Dist: python-dotenv>=1.0.0
Requires-Dist: pyyaml>=6.0.0
Requires-Dist: qdrant-client>=1.12.0
Requires-Dist: rich>=13.0.0
Requires-Dist: voyageai>=0.3.0
Provides-Extra: dev
Requires-Dist: pytest-asyncio>=0.24.0; extra == 'dev'
Requires-Dist: pytest>=8.0.0; extra == 'dev'
